atooms/backends/__init__.py
atooms/backends/dryrun.py
atooms/backends/lammps.py
atooms/backends/rumd.py
atooms/backends/f90/__init__.py
atooms/backends/f90/angle_harmonic.f90
atooms/backends/f90/bond_fene.f90
atooms/backends/f90/bond_harmonic.f90
atooms/backends/f90/cutoff_cubic_spline.f90
atooms/backends/f90/cutoff_cut.f90
atooms/backends/f90/cutoff_cut_shift.f90
atooms/backends/f90/cutoff_cut_shift_linear.f90
atooms/backends/f90/cutoff_cut_shift_quadratic.f90
atooms/backends/f90/helpers.f90
atooms/backends/f90/helpers.py
atooms/backends/f90/helpers_2d.f90
atooms/backends/f90/helpers_3d.f90
atooms/backends/f90/interaction.f90
atooms/backends/f90/interaction.py
atooms/backends/f90/interaction_intermolecular.f90
atooms/backends/f90/interaction_intramolecular.f90
atooms/backends/f90/interaction_molecular.f90
atooms/backends/f90/interaction_molecular.py
atooms/backends/f90/inverse_power_exp.f90
atooms/backends/f90/linked_cells.py
atooms/backends/f90/neighbor_list.f90
atooms/backends/f90/neighbor_list.py
atooms/backends/f90/trajectory.py
atooms/backends/f90/twobody_gaussian.f90
atooms/backends/f90/twobody_harmonic.f90
atooms/backends/f90/twobody_inverse_power.f90
atooms/backends/f90/twobody_lennard_jones.f90
atooms/backends/f90/twobody_sum_inverse_power.f90
atooms/backends/f90/twobody_yukawa.f90
atooms/backends/f90/verlet_list.py
atooms/core/__init__.py
atooms/core/_commit.py
atooms/core/_version.py
atooms/core/progress.py
atooms/core/utils.py
atooms/optimization/__init__.py
atooms/optimization/core.py
atooms/plugins/__init__.py
atooms/simulation/__init__.py
atooms/simulation/core.py
atooms/simulation/observers.py
atooms/simulation/reports.py
atooms/system/__init__.py
atooms/system/cell.py
atooms/system/interaction.py
atooms/system/molecule.py
atooms/system/particle.py
atooms/system/reservoir.py
atooms/system/system.py
atooms/system/topology.py
atooms/system/visualize.py
atooms/system/wall.py
atooms/trajectory/__init__.py
atooms/trajectory/base.py
atooms-3.28.3.dist-info/licenses/LICENSE
atooms-3.28.3.dist-info/METADATA
atooms-3.28.3.dist-info/WHEEL
atooms-3.28.3.dist-info/top_level.txt
atooms-3.28.3.dist-info/RECORD
