Metadata-Version: 2.4
Name: atooms
Version: 3.28.3
Summary: A framework for simulations of interacting particles
Author-email: Daniele Coslovich <daniele.coslovich@umontpellier.fr>
License: GPLv3
Project-URL: repository, https://framagit.org/atooms/atooms
Project-URL: homepage, https://framagit.org/atooms/atooms
Project-URL: documentation, https://atooms.frama.io/atooms
Project-URL: changelog, https://framagit.org/atooms/atooms/-/blob/master/CHANGELOG.md
Classifier: License :: OSI Approved :: GNU General Public License v3 (GPLv3)
Classifier: Development Status :: 5 - Production/Stable
Classifier: Programming Language :: Python :: 3
Classifier: Programming Language :: Python :: 3.7
Classifier: Programming Language :: Python :: 3.8
Classifier: Programming Language :: Python :: 3.9
Classifier: Programming Language :: Python :: 3.10
Classifier: Programming Language :: Python :: 3.11
Classifier: Programming Language :: Python :: 3.12
Classifier: Programming Language :: Python :: 3.13
Requires-Python: >=3.7
License-File: LICENSE
Requires-Dist: numpy<3,>=1.21.6
Requires-Dist: f2py_jit>=1.1.1
Provides-Extra: backends
Requires-Dist: h5py; extra == "backends"
Requires-Dist: gsd~=2.0; (python_version >= "3.13" or python_version == "3.8") and extra == "backends"
Requires-Dist: matplotlib; extra == "backends"
Requires-Dist: lammps; extra == "backends"
Dynamic: license-file
